{
  "id": "901",
  "nombre": "Tapa de Caja de Bornes Personalizada",
  "descripcion": "Tapa de repuesto para caja de bornes eléctrica. Diseñada a medida para sustituir tapas dañadas o perdidas.",
  "categoria": "otros",
  "estado": "revision",
  "autor": "Nombre del alumno",
  "curso": "2025-2026",
  "imagen": "piezas/otros/901-tapa-caja-bornes/preview.png",
  "archivos": {
    "stl": "piezas/otros/901-tapa-caja-bornes/pieza.stl",
    "plano": "piezas/otros/901-tapa-caja-bornes/plano.pdf"
  }
}
